eth_enr/__init__.py
eth_enr/abc.py
eth_enr/constants.py
eth_enr/constraints.py
eth_enr/enr.py
eth_enr/enr_db.py
eth_enr/enr_manager.py
eth_enr/exceptions.py
eth_enr/identity_schemes.py
eth_enr/py.typed
eth_enr/query_db.py
eth_enr/sedes.py
eth_enr/sqlite3_db.py
eth_enr/typing.py
eth_enr/tools/__init__.py
eth_enr/tools/factories.py
eth_enr-0.5.0.dist-info/LICENSE
eth_enr-0.5.0.dist-info/METADATA
eth_enr-0.5.0.dist-info/WHEEL
eth_enr-0.5.0.dist-info/top_level.txt
eth_enr-0.5.0.dist-info/RECORD
