Metadata-Version: 2.1
Name: eth-enr
Version: 0.5.0
Summary: eth-enr: Python library for ENR (EIP-778) records
Home-page: https://github.com/ethereum/eth-enr
Author: The Ethereum Foundation
Author-email: snakecharmers@ethereum.org
License: MIT
Keywords: ethereum
Platform: UNKNOWN
Classifier: Development Status :: 3 - Alpha
Classifier: Intended Audience :: Developers
Classifier: License :: OSI Approved :: MIT License
Classifier: Natural Language :: English
Classifier: Programming Language :: Python :: 3
Classifier: Programming Language :: Python :: 3.6
Classifier: Programming Language :: Python :: 3.7
Classifier: Programming Language :: Python :: 3.8
Requires-Python: >=3.6, <4
Requires-Dist: eth-hash[pycryptodome] (<1,>=0.1.4)
Requires-Dist: eth-keys (<0.4.0,>=0.3.3)
Requires-Dist: eth-utils (<2,>=1)
Requires-Dist: eth-typing (<3,>=2.2.2)
Requires-Dist: rlp (<3.0.0,>=2.0.0a1)
Provides-Extra: dev
Requires-Dist: bumpversion (<1,>=0.5.3) ; extra == 'dev'
Requires-Dist: pytest-watch (<5,>=4.1.0) ; extra == 'dev'
Requires-Dist: wheel ; extra == 'dev'
Requires-Dist: twine ; extra == 'dev'
Requires-Dist: ipython ; extra == 'dev'
Requires-Dist: factory-boy (==3.0.1) ; extra == 'dev'
Requires-Dist: pytest (==6.0.1) ; extra == 'dev'
Requires-Dist: pytest-xdist (==2.1.0) ; extra == 'dev'
Requires-Dist: tox (==3.19.0) ; extra == 'dev'
Requires-Dist: flake8 (==3.8.3) ; extra == 'dev'
Requires-Dist: isort (==5.4.2) ; extra == 'dev'
Requires-Dist: mypy (==0.782) ; extra == 'dev'
Requires-Dist: pydocstyle (<4,>=3.0.0) ; extra == 'dev'
Requires-Dist: black (==20.8b1) ; extra == 'dev'
Requires-Dist: Sphinx (<2,>=1.6.5) ; extra == 'dev'
Requires-Dist: sphinx-rtd-theme (>=0.1.9) ; extra == 'dev'
Requires-Dist: towncrier (<20,>=19.2.0) ; extra == 'dev'
Provides-Extra: doc
Requires-Dist: Sphinx (<2,>=1.6.5) ; extra == 'doc'
Requires-Dist: sphinx-rtd-theme (>=0.1.9) ; extra == 'doc'
Requires-Dist: towncrier (<20,>=19.2.0) ; extra == 'doc'
Provides-Extra: lint
Requires-Dist: flake8 (==3.8.3) ; extra == 'lint'
Requires-Dist: isort (==5.4.2) ; extra == 'lint'
Requires-Dist: mypy (==0.782) ; extra == 'lint'
Requires-Dist: pydocstyle (<4,>=3.0.0) ; extra == 'lint'
Requires-Dist: black (==20.8b1) ; extra == 'lint'
Provides-Extra: test
Requires-Dist: factory-boy (==3.0.1) ; extra == 'test'
Requires-Dist: pytest (==6.0.1) ; extra == 'test'
Requires-Dist: pytest-xdist (==2.1.0) ; extra == 'test'
Requires-Dist: tox (==3.19.0) ; extra == 'test'
